{"recipes":[{"name":"SALMON CALIFORNIA 4PC","sellingPrice":75.0,"ingredients":[{"ingredient":"CALIFORNIA ROLL","qty":4.0,"unit":"EACH","source_bulk_size":"8","source_unit_price":"R15.54"},{"ingredient":"SALMON","qty":20.0,"unit":"g","source_bulk_size":"700","source_unit_price":"R308.39"},{"ingredient":"SESAME SEED","qty":3.0,"unit":"g","source_bulk_size":"1000","source_unit_price":"R66.95"}],"page":1},{"name":"SALMON CALIFORNIA 8PC","sellingPrice":135.0,"ingredients":[{"ingredient":"CALIFORNIA ROLL","qty":8.0,"unit":"EACH","source_bulk_size":"8","source_unit_price":"R15.54"},{"ingredient":"SALMON","qty":40.0,"unit":"g","source_bulk_size":"700","source_unit_price":"R308.39"},{"ingredient":"SESAME SEED","qty":6.0,"unit":"g","source_bulk_size":"1000","source_unit_price":"R66.95"}],"page":1},{"name":"SALMON RAINBOW ROLL 4PC","sellingPrice":95.0,"ingredients":[{"ingredient":"CALIFORNIA ROLL","qty":4.0,"unit":"EACH","source_bulk_size":"8","source_unit_price":"R15.54"},{"ingredient":"SALMON","qty":30.0,"unit":"g","source_bulk_size":"700","source_unit_price":"R308.39"},{"ingredient":"AVO","qty":0.1,"unit":"EACH","source_bulk_size":"1","source_unit_price":"R21.25"}],"page":1},{"name":"SALMON RAINBOW ROLL 8PC","sellingPrice":165.0,"ingredients":[{"ingredient":"CALIFORNIA ROLL","qty":8.0,"unit":"EACH","source_bulk_size":"8","source_unit_price":"R15.54"},{"ingredient":"AVO","qty":0.2,"unit":"EACH","source_bulk_size":"1","source_unit_price":"R21.25"}],"page":1},{"name":"SALMON CRUNCH 4PC","sellingPrice":100.0,"ingredients":[{"ingredient":"CRUNCH ROLL","qty":4.0,"unit":"EACH","source_bulk_size":"8","source_unit_price":"R17.03"},{"ingredient":"SALMON","qty":20.0,"unit":"g","source_bulk_size":"700","source_unit_price":"R308.39"},{"ingredient":"PONZU MAYO","qty":5.0,"unit":"ml","source_bulk_size":"1000","source_unit_price":"R94.98"},{"ingredient":"TERIYAKI","qty":5.0,"unit":"g","source_bulk_size":"1000","source_unit_price":"R156.05"},{"ingredient":"SPRING ONION","qty":0.001,"unit":"EACH","source_bulk_size":"1","source_unit_price":"R16.45"},{"ingredient":"SESAME SEEDS","qty":0.1,"unit":"g","source_bulk_size":"1000","source_unit_price":"R66.95"}],"page":1},{"name":"SALMON CRUNCH 8PC","sellingPrice":0.0,"ingredients":[{"ingredient":"CRUNCH ROLL","qty":8.0,"unit":"EACH","source_bulk_size":"8","source_unit_price":"R17.03"},{"ingredient":"SALMON","qty":40.0,"unit":"g","source_bulk_size":"700","source_unit_price":"R308.39"},{"ingredient":"PONZU MAYO","qty":10.0,"unit":"ml","source_bulk_size":"1000","source_unit_price":"R94.98"},{"ingredient":"TERIYAKI","qty":10.0,"unit":"g","source_bulk_size":"1000","source_unit_price":"R156.05"},{"ingredient":"SPRING ONION","qty":0.001,"unit":"EACH","source_bulk_size":"1","source_unit_price":"R16.45"},{"ingredient":"SESAME SEEDS","qty":0.1,"unit":"g","source_bulk_size":"1000","source_unit_price":"R66.95"}],"page":1},{"name":"TUNA CALIFORNIA 4PC","sellingPrice":70.0,"ingredients":[{"ingredient":"CALIFORNIA ROLL","qty":4.0,"unit":"EACH","source_bulk_size":"8","source_unit_price":"R15.54"},{"ingredient":"TUNA","qty":20.0,"unit":"g","source_bulk_size":"900","source_unit_price":"R261.55"},{"ingredient":"SESAME SEED","qty":3.0,"unit":"g","source_bulk_size":"1000","source_unit_price":"R66.95"}],"page":1},{"name":"TUNA CALIFORNIA 8PC","sellingPrice":125.0,"ingredients":[{"ingredient":"CALIFORNIA ROLL","qty":8.0,"unit":"EACH","source_bulk_size":"8","source_unit_price":"R15.54"},{"ingredient":"TUNA","qty":40.0,"unit":"g","source_bulk_size":"900","source_unit_price":"R261.55"},{"ingredient":"SESAME SEED","qty":6.0,"unit":"g","source_bulk_size":"1000","source_unit_price":"R66.95"}],"page":1},{"name":"TUNA RAINBOW ROLL 4PC","sellingPrice":85.0,"ingredients":[{"ingredient":"CALIFORNIA ROLL","qty":4.0,"unit":"EACH","source_bulk_size":"8","source_unit_price":"R15.54"},{"ingredient":"TUNA","qty":30.0,"unit":"g","source_bulk_size":"900","source_unit_price":"R261.55"},{"ingredient":"AVO","qty":0.1,"unit":"EACH","source_bulk_size":"1","source_unit_price":"R21.25"}],"page":1},{"name":"TUNA RAINBOW ROLL 8PC","sellingPrice":155.0,"ingredients":[{"ingredient":"CALIFORNIA ROLL","qty":8.0,"unit":"EACH","source_bulk_size":"8","source_unit_price":"R15.54"},{"ingredient":"TUNA","qty":60.0,"unit":"g","source_bulk_size":"900","source_unit_price":"R261.55"},{"ingredient":"AVO","qty":0.2,"unit":"EACH","source_bulk_size":"1","source_unit_price":"R21.25"}],"page":1},{"name":"TUNA CRUNCH 4PC","sellingPrice":95.0,"ingredients":[{"ingredient":"CRUNCH ROLL","qty":4.0,"unit":"EACH","source_bulk_size":"8","source_unit_price":"R17.03"},{"ingredient":"TUNA","qty":20.0,"unit":"g","source_bulk_size":"900","source_unit_price":"R261.55"},{"ingredient":"PONZU MAYO","qty":5.0,"unit":"ml","source_bulk_size":"1000","source_unit_price":"R94.98"},{"ingredient":"TERIYAKI","qty":5.0,"unit":"g","source_bulk_size":"1000","source_unit_price":"R156.05"},{"ingredient":"SPRING ONION","qty":0.001,"unit":"EACH","source_bulk_size":"1","source_unit_price":"R16.45"},{"ingredient":"SESAME SEEDS","qty":0.1,"unit":"g","source_bulk_size":"1000","source_unit_price":"R66.95"}],"page":1},{"name":"TUNA CRUNCH 8PC","sellingPrice":0.0,"ingredients":[{"ingredient":"CRUNCH ROLL","qty":8.0,"unit":"EACH","source_bulk_size":"8","source_unit_price":"R17.03"},{"ingredient":"TUNA","qty":40.0,"unit":"g","source_bulk_size":"900","source_unit_price":"R261.55"},{"ingredient":"PONZU MAYO","qty":10.0,"unit":"ml","source_bulk_size":"1000","source_unit_price":"R94.98"},{"ingredient":"TERIYAKI","qty":10.0,"unit":"g","source_bulk_size":"1000","source_unit_price":"R156.05"},{"ingredient":"SPRING ONION","qty":0.001,"unit":"EACH","source_bulk_size":"1","source_unit_price":"R16.45"},{"ingredient":"SESAME SEEDS","qty":0.1,"unit":"g","source_bulk_size":"1000","source_unit_price":"R66.95"}],"page":1},{"name":"PRAWN CALIFORNIA 4PC","sellingPrice":70.0,"ingredients":[{"ingredient":"CALIFORNIA ROLL","qty":4.0,"unit":"EACH","source_bulk_size":"8","source_unit_price":"R15.54"},{"ingredient":"PRAWN","qty":20.0,"unit":"g","source_bulk_size":"900","source_unit_price":"R284.04"},{"ingredient":"SESAME SEED","qty":3.0,"unit":"g","source_bulk_size":"1000","source_unit_price":"R66.95"}],"page":1},{"name":"PRAWN CALIFORNIA 8PC","sellingPrice":125.0,"ingredients":[{"ingredient":"CALIFORNIA ROLL","qty":8.0,"unit":"EACH","source_bulk_size":"8","source_unit_price":"R15.54"},{"ingredient":"PRAWN","qty":40.0,"unit":"g","source_bulk_size":"900","source_unit_price":"R284.04"},{"ingredient":"SESAME SEED","qty":6.0,"unit":"g","source_bulk_size":"1000","source_unit_price":"R66.95"}],"page":1},{"name":"PRAWN RAINBOW ROLL 4PC","sellingPrice":85.0,"ingredients":[{"ingredient":"CALIFORNIA ROLL","qty":4.0,"unit":"EACH","source_bulk_size":"8","source_unit_price":"R15.54"},{"ingredient":"PRAWN","qty":30.0,"unit":"g","source_bulk_size":"900","source_unit_price":"R284.04"},{"ingredient":"AVO","qty":0.1,"unit":"EACH","source_bulk_size":"1","source_unit_price":"R21.25"}],"page":1},{"name":"PRAWN RAINBOW ROLL 8PC","sellingPrice":155.0,"ingredients":[{"ingredient":"CALIFORNIA ROLL","qty":8.0,"unit":"EACH","source_bulk_size":"8","source_unit_price":"R15.54"},{"ingredient":"PRAWN","qty":60.0,"unit":"g","source_bulk_size":"900","source_unit_price":"R284.04"},{"ingredient":"AVO","qty":0.2,"unit":"EACH","source_bulk_size":"1","source_unit_price":"R21.25"}],"page":1},{"name":"PRAWN CRUNCH 4PC","sellingPrice":95.0,"ingredients":[{"ingredient":"CRUNCH ROLL","qty":4.0,"unit":"EACH","source_bulk_size":"8","source_unit_price":"R17.03"},{"ingredient":"PRAWN","qty":60.0,"unit":"g","source_bulk_size":"900","source_unit_price":"R284.04"},{"ingredient":"PONZU MAYO","qty":5.0,"unit":"ml","source_bulk_size":"1000","source_unit_price":"R94.98"},{"ingredient":"TERIYAKI","qty":5.0,"unit":"g","source_bulk_size":"1000","source_unit_price":"R156.05"},{"ingredient":"SPRING ONION","qty":0.001,"unit":"EACH","source_bulk_size":"1","source_unit_price":"R16.45"},{"ingredient":"SESAME SEEDS","qty":0.1,"unit":"g","source_bulk_size":"1000","source_unit_price":"R66.95"}],"page":1},{"name":"PRAWN CRUNCH 8PC","sellingPrice":0.0,"ingredients":[{"ingredient":"CRUNCH ROLL","qty":8.0,"unit":"EACH","source_bulk_size":"8","source_unit_price":"R17.03"},{"ingredient":"PRAWN","qty":120.0,"unit":"g","source_bulk_size":"900","source_unit_price":"R284.04"},{"ingredient":"PONZU MAYO","qty":10.0,"unit":"ml","source_bulk_size":"1000","source_unit_price":"R94.98"},{"ingredient":"TERIYAKI","qty":10.0,"unit":"g","source_bulk_size":"1000","source_unit_price":"R156.05"},{"ingredient":"SPRING ONION","qty":0.001,"unit":"EACH","source_bulk_size":"1","source_unit_price":"R16.45"},{"ingredient":"SESAME SEEDS","qty":0.1,"unit":"g","source_bulk_size":"1000","source_unit_price":"R66.95"}],"page":1},{"name":"AVO CALIFORNIA 4PC","sellingPrice":65.0,"ingredients":[{"ingredient":"CALIFORNIA ROLL","qty":4.0,"unit":"EACH","source_bulk_size":"8","source_unit_price":"R15.54"},{"ingredient":"AVO","qty":0.25,"unit":"EACH","source_bulk_size":"1","source_unit_price":"R21.25"},{"ingredient":"SESAME SEED","qty":3.0,"unit":"g","source_bulk_size":"1000","source_unit_price":"R66.95"}],"page":1},{"name":"AVO CALIFORNIA 8PC","sellingPrice":120.0,"ingredients":[{"ingredient":"CALIFORNIA ROLL","qty":8.0,"unit":"EACH","source_bulk_size":"8","source_unit_price":"R15.54"},{"ingredient":"AVO","qty":0.33,"unit":"EACH","source_bulk_size":"1","source_unit_price":"R21.25"},{"ingredient":"SESAME SEED","qty":6.0,"unit":"g","source_bulk_size":"1000","source_unit_price":"R66.95"}],"page":1},{"name":"MONARCH RAINBOW ROLL 4PC","sellingPrice":70.0,"ingredients":[{"ingredient":"CALIFORNIA ROLL","qty":4.0,"unit":"EACH","source_bulk_size":"8","source_unit_price":"R15.54"},{"ingredient":"AVO","qty":0.33,"unit":"EACH","source_bulk_size":"1","source_unit_price":"R21.25"},{"ingredient":"RED PEPPER","qty":5.0,"unit":"g","source_bulk_size":"1000","source_unit_price":"R92.65"},{"ingredient":"CARROT","qty":5.0,"unit":"g","source_bulk_size":"1000","source_unit_price":"R17.25"},{"ingredient":"CUCUMBER","qty":0.1,"unit":"EACH","source_bulk_size":"1","source_unit_price":"R17.85"},{"ingredient":"VEG MIX","qty":5.0,"unit":"g","source_bulk_size":"1000.00","source_unit_price":"R60.59"}],"page":1},{"name":"MONARCH RAINBOW ROLL 8PC","sellingPrice":125.0,"ingredients":[{"ingredient":"CALIFORNIA ROLL","qty":8.0,"unit":"EACH","source_bulk_size":"8","source_unit_price":"R15.54"},{"ingredient":"AVO","qty":0.66,"unit":"EACH","source_bulk_size":"1","source_unit_price":"R21.25"},{"ingredient":"RED PEPPER","qty":10.0,"unit":"g","source_bulk_size":"1000","source_unit_price":"R92.65"},{"ingredient":"CARROT","qty":10.0,"unit":"g","source_bulk_size":"1000","source_unit_price":"R17.25"},{"ingredient":"CUCUMBER","qty":0.2,"unit":"EACH","source_bulk_size":"1","source_unit_price":"R17.85"},{"ingredient":"VEG MIX NEW","qty":10.0,"unit":"g","source_bulk_size":"1000.00","source_unit_price":"R60.59"}],"page":1},{"name":"VEG CRUNCH 4PC","sellingPrice":85.0,"ingredients":[{"ingredient":"CRUNCH ROLL","qty":4.0,"unit":"EACH","source_bulk_size":"8","source_unit_price":"R17.03"},{"ingredient":"AVO","qty":0.16,"unit":"g","source_bulk_size":"700","source_unit_price":"R21.25"},{"ingredient":"PONZU MAYO","qty":5.0,"unit":"ml","source_bulk_size":"1000","source_unit_price":"R94.98"},{"ingredient":"TERIYAKI","qty":5.0,"unit":"g","source_bulk_size":"1000","source_unit_price":"R156.05"},{"ingredient":"SPRING ONION","qty":0.001,"unit":"EACH","source_bulk_size":"1","source_unit_price":"R16.45"},{"ingredient":"SESAME SEEDS","qty":0.1,"unit":"g","source_bulk_size":"1000","source_unit_price":"R66.95"}],"page":1},{"name":"VEG CRUNCH 8PC","sellingPrice":0.0,"ingredients":[{"ingredient":"CRUNCH ROLL","qty":8.0,"unit":"EACH","source_bulk_size":"8","source_unit_price":"R17.03"},{"ingredient":"AVO","qty":0.5,"unit":"EACH","source_bulk_size":"1","source_unit_price":"R21.25"},{"ingredient":"PONZU MAYO","qty":10.0,"unit":"ml","source_bulk_size":"1000","source_unit_price":"R94.98"},{"ingredient":"TERIYAKI","qty":10.0,"unit":"g","source_bulk_size":"1000","source_unit_price":"R156.05"},{"ingredient":"SPRING ONION","qty":0.001,"unit":"EACH","source_bulk_size":"1","source_unit_price":"#REF!"},{"ingredient":"SESAME SEEDS","qty":0.1,"unit":"g","source_bulk_size":"1000","source_unit_price":"R66.95"}],"page":1},{"name":"GARNISH","sellingPrice":0.0,"ingredients":[{"ingredient":"SOYA SAUCE","qty":25.0,"unit":"ml","source_bulk_size":"1000","source_unit_price":"R135.00"},{"ingredient":"GINGER","qty":20.0,"unit":"g","source_bulk_size":"1000","source_unit_price":"R35.30"},{"ingredient":"WASABI","qty":10.0,"unit":"g","source_bulk_size":"1000","source_unit_price":"R134.95"},{"ingredient":"BEETROOT","qty":5.0,"unit":"g","source_bulk_size":"1000","source_unit_price":"19.99"},{"ingredient":"CARROTS","qty":5.0,"unit":"g","source_bulk_size":"1000","source_unit_price":"R17.25"},{"ingredient":"CANDY BEETROOT","qty":5.0,"unit":"g","source_bulk_size":"1000","source_unit_price":"R50.00"},{"ingredient":"WATERMELON RADISH","qty":5.0,"unit":"g","source_bulk_size":"1000","source_unit_price":"51.75"}],"page":1},{"name":"FUSION RELOADED 8PC","sellingPrice":190.0,"ingredients":[{"ingredient":"CALIFORNIA","qty":8.0,"unit":"EACH","source_bulk_size":"8","source_unit_price":"R15.54"},{"ingredient":"SALMON","qty":15.0,"unit":"g","source_bulk_size":"700","source_unit_price":"R10.65"},{"ingredient":"TUNA MIX","qty":40.0,"unit":"g","source_bulk_size":"125","source_unit_price":"R1.54"},{"ingredient":"TUNA","qty":15.0,"unit":"g","source_bulk_size":"900","source_unit_price":"R261.55"},{"ingredient":"COOKED PRAWN","qty":60.0,"unit":"g","source_bulk_size":"900","source_unit_price":"R284.04"},{"ingredient":"NORI","qty":1.0,"unit":"g","source_bulk_size":"100","source_unit_price":"R3.10"},{"ingredient":"TERIYAKI","qty":10.0,"unit":"g","source_bulk_size":"1000","source_unit_price":"R156.05"},{"ingredient":"TOGARASHI","qty":6.0,"unit":"g","source_bulk_size":"300","source_unit_price":"R342.99"},{"ingredient":"SPRING ONION","qty":0.006,"unit":"EACH","source_bulk_size":"1","source_unit_price":"R16.45"},{"ingredient":"JAPANESE MAYO","qty":10.0,"unit":"ml","source_bulk_size":"500","source_unit_price":"R175.53"},{"ingredient":"SESAME","qty":6.0,"unit":"g","source_bulk_size":"1000","source_unit_price":"R66.95"},{"ingredient":"CAVIAR","qty":3.0,"unit":"g","source_bulk_size":"1000","source_unit_price":"R2,199.80"}],"page":1},{"name":"PRAWN ROLL 4PC","sellingPrice":98.0,"ingredients":[{"ingredient":"CALIFORNIA ROLL 8PC","qty":4.0,"unit":"EACH","source_bulk_size":"8","source_unit_price":"R15.54"},{"ingredient":"TEMPURA PRAWN","qty":4.0,"unit":"g","source_bulk_size":"1000","source_unit_price":"R7.40"},{"ingredient":"TSUNAMI SAUCE","qty":15.0,"unit":"ml","source_bulk_size":"500","source_unit_price":"R277.60"},{"ingredient":"SPRING ONION","qty":0.003,"unit":"EACH","source_bulk_size":"1","source_unit_price":"R16.45"},{"ingredient":"SESAME SEEDS","qty":6.0,"unit":"g","source_bulk_size":"1000","source_unit_price":"R66.95"}],"page":1},{"name":"PRAWN ROLL 8PC","sellingPrice":195.0,"ingredients":[{"ingredient":"CALIFORNIA ROLL 8PC","qty":8.0,"unit":"EACH","source_bulk_size":"8","source_unit_price":"R15.54"},{"ingredient":"TEMPURA PRAWN","qty":4.0,"unit":"g","source_bulk_size":"1000","source_unit_price":"R7.40"},{"ingredient":"TSUNAMI SAUCE","qty":30.0,"unit":"ml","source_bulk_size":"500","source_unit_price":"R277.60"},{"ingredient":"SPRING ONION","qty":0.006,"unit":"EACH","source_bulk_size":"1","source_unit_price":"R16.45"},{"ingredient":"SESAME SEEDS","qty":6.0,"unit":"g","source_bulk_size":"1000","source_unit_price":"R66.95"}],"page":1},{"name":"FUTOMAKI 3PC","sellingPrice":85.0,"ingredients":[{"ingredient":"SUSHI RICE","qty":50.0,"unit":"g","source_bulk_size":"1000","source_unit_price":""},{"ingredient":"SALMON","qty":12.5,"unit":"g","source_bulk_size":"700","source_unit_price":"R10.65"},{"ingredient":"AVO","qty":10.0,"unit":"g","source_bulk_size":"120","source_unit_price":"R21.25"},{"ingredient":"PICKLED ONION","qty":8.0,"unit":"g","source_bulk_size":"500","source_unit_price":""},{"ingredient":"SESAME SEEDS","qty":0.1,"unit":"g","source_bulk_size":"1000","source_unit_price":"R66.95"},{"ingredient":"TERIYAKI","qty":5.0,"unit":"g","source_bulk_size":"1000","source_unit_price":"R156.05"},{"ingredient":"PONZU MAYO","qty":5.0,"unit":"ml","source_bulk_size":"1000","source_unit_price":"R94.98"},{"ingredient":"TOGARASHI","qty":1.0,"unit":"g","source_bulk_size":"300","source_unit_price":"R342.99"}],"page":1},{"name":"FUTOMAKI 6PC","sellingPrice":0.0,"ingredients":[{"ingredient":"SUSHI RICE","qty":100.0,"unit":"g","source_bulk_size":"1000","source_unit_price":"R24.03"},{"ingredient":"SALMON","qty":25.0,"unit":"g","source_bulk_size":"700","source_unit_price":"R10.65"},{"ingredient":"AVO","qty":20.0,"unit":"g","source_bulk_size":"120","source_unit_price":"R21.25"},{"ingredient":"PICKLED ONION","qty":15.0,"unit":"g","source_bulk_size":"500","source_unit_price":""},{"ingredient":"SESAME SEEDS","qty":0.1,"unit":"g","source_bulk_size":"1000","source_unit_price":"R66.95"},{"ingredient":"TERIYAKI","qty":10.0,"unit":"g","source_bulk_size":"1000","source_unit_price":"R156.05"},{"ingredient":"PONZU MAYO","qty":10.0,"unit":"ml","source_bulk_size":"1000","source_unit_price":"R94.98"},{"ingredient":"TOGARASHI","qty":1.0,"unit":"g","source_bulk_size":"300","source_unit_price":"R342.99"}],"page":1},{"name":"GARDEN OF EDEN 14PC","sellingPrice":220.0,"ingredients":[{"ingredient":"AVO CILAFORNIA ROLL","qty":4.0,"unit":"EACH","source_bulk_size":"8","source_unit_price":"R15.28"},{"ingredient":"PINK BUTTERFLY","qty":4.0,"unit":"EACH","source_bulk_size":"8","source_unit_price":"R27.77"},{"ingredient":"MONARCH RAINBOW ROLL","qty":4.0,"unit":"EACH","source_bulk_size":"8","source_unit_price":"R19.42"},{"ingredient":"VEG ROSES","qty":2.0,"unit":"EACH","source_bulk_size":"2","source_unit_price":"R10.46"}],"page":1},{"name":"BLU COAST 13PC","sellingPrice":290.0,"ingredients":[{"ingredient":"SALMON CALIFORNIA","qty":4.0,"unit":"EACH","source_bulk_size":"4","source_unit_price":"R18.78"},{"ingredient":"PRAWN ROLL","qty":4.0,"unit":"EACH","source_bulk_size":"4","source_unit_price":"R18.58"},{"ingredient":"FUTOMAKI","qty":3.0,"unit":"EACH","source_bulk_size":"3","source_unit_price":"R6.37"},{"ingredient":"PRAWN NIGIRI","qty":2.0,"unit":"EACH","source_bulk_size":"2","source_unit_price":"R18.74"}],"page":1},{"name":"INDIAN OCEAN PLATTER 16PC","sellingPrice":395.0,"ingredients":[{"ingredient":"PRAWN CALIFORNIA","qty":4.0,"unit":"EACH","source_bulk_size":"4","source_unit_price":"R16.28"},{"ingredient":"TUNA NIGIRI","qty":2.0,"unit":"EACH","source_bulk_size":"2","source_unit_price":"R11.68"},{"ingredient":"ROCK SHRIMP ROSES","qty":2.0,"unit":"EACH","source_bulk_size":"4","source_unit_price":"R6.03"},{"ingredient":"PRAWN ROLL","qty":4.0,"unit":"EACH","source_bulk_size":"4","source_unit_price":"R18.58"},{"ingredient":"SALMON TEMPURA","qty":4.0,"unit":"EACH","source_bulk_size":"4","source_unit_price":"R20.60"}],"page":1},{"name":"BRENTON SEA PLATTER 20PC","sellingPrice":480.0,"ingredients":[{"ingredient":"SALMON CALIFORNIA","qty":4.0,"unit":"EACH","source_bulk_size":"4","source_unit_price":"R18.78"},{"ingredient":"PRAWN ROLL","qty":4.0,"unit":"EACH","source_bulk_size":"4","source_unit_price":"R18.58"},{"ingredient":"FUTOMAKI","qty":3.0,"unit":"EACH","source_bulk_size":"3","source_unit_price":"R6.37"},{"ingredient":"PRAWN TEMPURA","qty":5.0,"unit":"EACH","source_bulk_size":"4","source_unit_price":"R30.73"},{"ingredient":"TUNA NIGIRI","qty":2.0,"unit":"EACH","source_bulk_size":"2","source_unit_price":"R11.68"},{"ingredient":"ROCK SHRIMP","qty":2.0,"unit":"EACH","source_bulk_size":"4","source_unit_price":"R6.03"}],"page":1},{"name":"BUTTERFLY RAINBOW PLATTER 26PC","sellingPrice":595.0,"ingredients":[{"ingredient":"SALMON CALIFORNIA","qty":4.0,"unit":"EACH","source_bulk_size":"4","source_unit_price":"R18.78"},{"ingredient":"TUNA RAINBOW","qty":4.0,"unit":"EACH","source_bulk_size":"4","source_unit_price":"R20.61"},{"ingredient":"TUNA MAKI","qty":4.0,"unit":"EACH","source_bulk_size":"4","source_unit_price":"R8.79"},{"ingredient":"PRAWN ROLL","qty":4.0,"unit":"EACH","source_bulk_size":"4","source_unit_price":"R18.58"},{"ingredient":"ROCK SHRIMP ROSES","qty":2.0,"unit":"EACH","source_bulk_size":"4","source_unit_price":"R6.03"},{"ingredient":"SALMON SASHIMI","qty":3.0,"unit":"EACH","source_bulk_size":"3","source_unit_price":"R90.28"},{"ingredient":"PRAWN NIGIRI","qty":2.0,"unit":"EACH","source_bulk_size":"2","source_unit_price":"R18.74"},{"ingredient":"FUTOMAKI","qty":3.0,"unit":"EACH","source_bulk_size":"3","source_unit_price":"R6.37"}],"page":1},{"name":"DELUXE PLATTER 26PC","sellingPrice":0.0,"ingredients":[{"ingredient":"MONARCH","qty":4.0,"unit":"EACH","source_bulk_size":"4","source_unit_price":"R19.42"},{"ingredient":"AVO CALIFORNIA","qty":4.0,"unit":"EACH","source_bulk_size":"4","source_unit_price":"R15.28"},{"ingredient":"PRAWN SANDWICH","qty":4.0,"unit":"EACH","source_bulk_size":"4","source_unit_price":"R17.47"},{"ingredient":"SALMON SASHIMI","qty":2.0,"unit":"EACH","source_bulk_size":"3","source_unit_price":"R0.83"},{"ingredient":"TUNA SASHIMI","qty":2.0,"unit":"EACH","source_bulk_size":"3","source_unit_price":"R19.60"},{"ingredient":"PRAWN NIGIRI","qty":2.0,"unit":"EACH","source_bulk_size":"3","source_unit_price":"R18.74"},{"ingredient":"SALMON NIGIRI","qty":2.0,"unit":"EACH","source_bulk_size":"2","source_unit_price":"R16.18"},{"ingredient":"MINI CRAB MISO","qty":0.5,"unit":"EACH","source_bulk_size":"1","source_unit_price":"R82.74"},{"ingredient":"SALMON ROSES","qty":4.0,"unit":"EACH","source_bulk_size":"4.00","source_unit_price":"R37.62"}],"page":1},{"name":"SALMON SASHIMI 3PC","sellingPrice":125.0,"ingredients":[{"ingredient":"SALMON","qty":200.0,"unit":"g","source_bulk_size":"700","source_unit_price":"R308.39"},{"ingredient":"LETTUCE","qty":5.0,"unit":"g","source_bulk_size":"1000","source_unit_price":"R26.99"},{"ingredient":"SUSHI GARNISH","qty":5.0,"unit":"g","source_bulk_size":"1000","source_unit_price":"R6.13"}],"page":2},{"name":"SALMON NIGIRI 2PC","sellingPrice":70.0,"ingredients":[{"ingredient":"SALMON","qty":30.0,"unit":"g","source_bulk_size":"700","source_unit_price":"R308.39"},{"ingredient":"SUSHI RICE","qty":40.0,"unit":"g","source_bulk_size":"1000","source_unit_price":"R24.03"}],"page":2},{"name":"SALMON MAKI 4PC","sellingPrice":60.0,"ingredients":[{"ingredient":"SALMON","qty":20.0,"unit":"g","source_bulk_size":"700","source_unit_price":"R308.39"},{"ingredient":"SUSHI RICE","qty":40.0,"unit":"g","source_bulk_size":"1000","source_unit_price":"R24.03"},{"ingredient":"NORI","qty":0.5,"unit":"g","source_bulk_size":"100","source_unit_price":"R3.10"}],"page":2},{"name":"SALMON FASHION SANDWICH 4PC","sellingPrice":80.0,"ingredients":[{"ingredient":"SALMON","qty":30.0,"unit":"g","source_bulk_size":"700","source_unit_price":"R308.39"},{"ingredient":"SUSHI RICE","qty":120.0,"unit":"g","source_bulk_size":"1000","source_unit_price":"R24.03"},{"ingredient":"NORI","qty":0.25,"unit":"g","source_bulk_size":"50","source_unit_price":"R3.10"},{"ingredient":"JAPANESE MAYO","qty":4.0,"unit":"ml","source_bulk_size":"500","source_unit_price":"R175.53"},{"ingredient":"AVO","qty":0.125,"unit":"EACH","source_bulk_size":"1","source_unit_price":"R21.25"}],"page":2},{"name":"SEARED SALMON SASHIMI","sellingPrice":120.0,"ingredients":[{"ingredient":"SALMON","qty":60.0,"unit":"g","source_bulk_size":"700","source_unit_price":"R308.39"},{"ingredient":"SEASONAL SALSA","qty":30.0,"unit":"g","source_bulk_size":"1000","source_unit_price":"R74.12"},{"ingredient":"GARNISH","qty":10.0,"unit":"g","source_bulk_size":"100","source_unit_price":"R6.13"},{"ingredient":"LETTUCE","qty":5.0,"unit":"g","source_bulk_size":"500","source_unit_price":"R26.99"},{"ingredient":"CAVIAR","qty":3.0,"unit":"g","source_bulk_size":"100","source_unit_price":"R202.75"}],"page":2},{"name":"REGULAR ROSES 4PC","sellingPrice":0.0,"ingredients":[{"ingredient":"SUSHI RICE","qty":40.0,"unit":"g","source_bulk_size":"1000","source_unit_price":"R24.03"},{"ingredient":"SALMON","qty":40.0,"unit":"g","source_bulk_size":"700","source_unit_price":"R308.39"},{"ingredient":"AVO","qty":0.01,"unit":"EACH","source_bulk_size":"1","source_unit_price":"R21.25"},{"ingredient":"JAPANESE MAYO","qty":0.2,"unit":"ml","source_bulk_size":"500","source_unit_price":"R175.53"},{"ingredient":"CAVIAR","qty":1.0,"unit":"g","source_bulk_size":"100","source_unit_price":"R202.75"}],"page":2},{"name":"TUNA SASHIMI 3PC","sellingPrice":110.0,"ingredients":[{"ingredient":"TUNA","qty":60.0,"unit":"g","source_bulk_size":"900","source_unit_price":"R261.55"},{"ingredient":"LETTUCE","qty":5.0,"unit":"g","source_bulk_size":"1000","source_unit_price":"R26.99"},{"ingredient":"SUSHI GARNISH","qty":5.0,"unit":"g","source_bulk_size":"1000","source_unit_price":"R6.13"}],"page":2},{"name":"TUNA NIGIRI 2PC","sellingPrice":65.0,"ingredients":[{"ingredient":"TUNA","qty":30.0,"unit":"g","source_bulk_size":"900","source_unit_price":"R261.55"},{"ingredient":"SUSHI RICE","qty":40.0,"unit":"g","source_bulk_size":"1000","source_unit_price":"R24.03"}],"page":2},{"name":"TUNA MAKI 4PC","sellingPrice":55.0,"ingredients":[{"ingredient":"TUNA","qty":20.0,"unit":"g","source_bulk_size":"900.00","source_unit_price":"R261.55"},{"ingredient":"SUSHI RICE","qty":40.0,"unit":"g","source_bulk_size":"1000","source_unit_price":"R24.03"},{"ingredient":"NORI","qty":0.5,"unit":"g","source_bulk_size":"100","source_unit_price":"R3.10"}],"page":2},{"name":"TUNA FASHION SANDWICH4PC","sellingPrice":80.0,"ingredients":[{"ingredient":"TUNA","qty":30.0,"unit":"g","source_bulk_size":"900","source_unit_price":"R261.55"},{"ingredient":"SUSHI RICE","qty":120.0,"unit":"g","source_bulk_size":"1000","source_unit_price":"R24.03"},{"ingredient":"NORI","qty":0.25,"unit":"g","source_bulk_size":"100.00","source_unit_price":"R3.10"},{"ingredient":"JAPANESE MAYO","qty":4.0,"unit":"ml","source_bulk_size":"500","source_unit_price":"R175.53"},{"ingredient":"AVO","qty":0.125,"unit":"EACH","source_bulk_size":"1","source_unit_price":"R21.25"}],"page":2},{"name":"SEARED TUNA SASHIMI","sellingPrice":120.0,"ingredients":[{"ingredient":"TUNA","qty":30.0,"unit":"g","source_bulk_size":"900","source_unit_price":"R240.00"}],"page":2},{"name":"OTORO NIGIRI","sellingPrice":0.0,"ingredients":[{"ingredient":"TUNA","qty":30.0,"unit":"g","source_bulk_size":"900","source_unit_price":"R240.00"},{"ingredient":"SUSHI RICE","qty":40.0,"unit":"g","source_bulk_size":"1000","source_unit_price":"R24.03"}],"page":2},{"name":"PRAWN NIGIRI 2PC","sellingPrice":70.0,"ingredients":[{"ingredient":"PRAWN","qty":50.0,"unit":"g","source_bulk_size":"900","source_unit_price":"R284.04"},{"ingredient":"SUSHI RICE","qty":40.0,"unit":"g","source_bulk_size":"1000","source_unit_price":"R24.03"}],"page":2},{"name":"PRAWN MAKI 4PC","sellingPrice":60.0,"ingredients":[{"ingredient":"PRAWN","qty":25.0,"unit":"g","source_bulk_size":"900.00","source_unit_price":"R284.04"},{"ingredient":"SUSHI RICE","qty":40.0,"unit":"g","source_bulk_size":"1000","source_unit_price":"R24.03"},{"ingredient":"NORI","qty":0.5,"unit":"g","source_bulk_size":"100","source_unit_price":"R3.10"}],"page":2},{"name":"PRAWN FASHION SANDWICHI 4PC","sellingPrice":80.0,"ingredients":[{"ingredient":"PRAWN","qty":30.0,"unit":"g","source_bulk_size":"1000","source_unit_price":"R284.04"},{"ingredient":"SUSHI RICE","qty":120.0,"unit":"g","source_bulk_size":"1000","source_unit_price":"R24.03"},{"ingredient":"NORI","qty":0.25,"unit":"g","source_bulk_size":"100.00","source_unit_price":"R3.10"},{"ingredient":"JAPANESE MAYO","qty":4.0,"unit":"ml","source_bulk_size":"500","source_unit_price":"R175.53"},{"ingredient":"AVO","qty":0.125,"unit":"EACH","source_bulk_size":"1","source_unit_price":"R21.25"}],"page":2},{"name":"AVO NIGIRI 2PC","sellingPrice":65.0,"ingredients":[{"ingredient":"AVO","qty":0.25,"unit":"EACH","source_bulk_size":"1","source_unit_price":"R21.25"},{"ingredient":"SUSHI RICE","qty":40.0,"unit":"g","source_bulk_size":"1000","source_unit_price":"R24.03"}],"page":2},{"name":"AVO MAKI 4PC","sellingPrice":40.0,"ingredients":[{"ingredient":"AVO","qty":0.16,"unit":"EACH","source_bulk_size":"1.00","source_unit_price":"R21.25"},{"ingredient":"SUSHI RICE","qty":40.0,"unit":"g","source_bulk_size":"1000","source_unit_price":"R24.03"},{"ingredient":"NORI","qty":0.5,"unit":"g","source_bulk_size":"100","source_unit_price":"3.10"}],"page":2},{"name":"AVO FASHION SANDWICH 4PC","sellingPrice":75.0,"ingredients":[{"ingredient":"AVO","qty":0.125,"unit":"EACH","source_bulk_size":"1","source_unit_price":"R21.25"},{"ingredient":"SUSHI RICE","qty":120.0,"unit":"g","source_bulk_size":"1000","source_unit_price":"R24.03"},{"ingredient":"NORI","qty":0.25,"unit":"g","source_bulk_size":"100.00","source_unit_price":"R3.10"},{"ingredient":"JAPANESE MAYO","qty":4.0,"unit":"ml","source_bulk_size":"500","source_unit_price":"R175.53"}],"page":2},{"name":"ROCK SHRIMP ROSES 4PC","sellingPrice":135.0,"ingredients":[{"ingredient":"SUSHI RICE","qty":40.0,"unit":"g","source_bulk_size":"1000","source_unit_price":"R24.03"},{"ingredient":"SALMON","qty":40.0,"unit":"g","source_bulk_size":"700","source_unit_price":"R10.65"},{"ingredient":"AVO","qty":0.1,"unit":"EACH","source_bulk_size":"1","source_unit_price":"R21.25"},{"ingredient":"ROCK SHRIMP MIX","qty":25.0,"unit":"g","source_bulk_size":"120","source_unit_price":"R1.60"}],"page":2},{"name":"CURED SALMON ROSES 4PC","sellingPrice":120.0,"ingredients":[{"ingredient":"CURED SALMON","qty":4.0,"unit":"EACH","source_bulk_size":"4","source_unit_price":"R23.59"},{"ingredient":"RICE","qty":40.0,"unit":"g","source_bulk_size":"1000","source_unit_price":"R24.03"},{"ingredient":"AVO","qty":0.0,"unit":"EACH","source_bulk_size":"1","source_unit_price":"R21.25"},{"ingredient":"JAPANESE MAYO","qty":20.0,"unit":"ml","source_bulk_size":"500","source_unit_price":"R175.53"},{"ingredient":"MICRO GREENS","qty":5.0,"unit":"g","source_bulk_size":"1000","source_unit_price":"#REF!"}],"page":2},{"name":"TUNA ROSES 4PC","sellingPrice":120.0,"ingredients":[{"ingredient":"TUNA","qty":40.0,"unit":"g","source_bulk_size":"900","source_unit_price":"R261.55"},{"ingredient":"RICE","qty":40.0,"unit":"g","source_bulk_size":"1000","source_unit_price":"R24.03"},{"ingredient":"AVO","qty":0.1,"unit":"EACH","source_bulk_size":"1","source_unit_price":"R21.25"},{"ingredient":"TSUNAMI SAUCE","qty":20.0,"unit":"ml","source_bulk_size":"500","source_unit_price":"R277.60"},{"ingredient":"SPRING ONION","qty":0.0,"unit":"EACH","source_bulk_size":"1","source_unit_price":"R16.45"}],"page":2},{"name":"VEG ROSES 4PC","sellingPrice":90.0,"ingredients":[{"ingredient":"CUCUMBER","qty":0.0,"unit":"EACH","source_bulk_size":"1","source_unit_price":"R17.85"},{"ingredient":"RICE","qty":40.0,"unit":"g","source_bulk_size":"1000","source_unit_price":"R24.03"},{"ingredient":"AVO","qty":0.0,"unit":"EACH","source_bulk_size":"1","source_unit_price":"R21.25"},{"ingredient":"VEG MIX NEW","qty":15.0,"unit":"g","source_bulk_size":"1000","source_unit_price":"R60.59"}],"page":2},{"name":"TIGER ROLL 8PC","sellingPrice":210.0,"ingredients":[{"ingredient":"CALIFORNIA ROLL","qty":8.0,"unit":"EACH","source_bulk_size":"8","source_unit_price":"R15.54"},{"ingredient":"SMOKED SALMON","qty":30.0,"unit":"g","source_bulk_size":"1000","source_unit_price":"R508.11"},{"ingredient":"AVO","qty":0.25,"unit":"EACH","source_bulk_size":"1","source_unit_price":"R21.25"},{"ingredient":"CREAM CHEESE","qty":10.0,"unit":"ml","source_bulk_size":"1000","source_unit_price":"R98.00"},{"ingredient":"PRAWN","qty":60.0,"unit":"g","source_bulk_size":"900","source_unit_price":"R284.04"},{"ingredient":"JAPANESE MAYO","qty":10.0,"unit":"ml","source_bulk_size":"500","source_unit_price":"R175.53"},{"ingredient":"CAVIAR","qty":3.0,"unit":"g","source_bulk_size":"1000","source_unit_price":"R2,199.80"},{"ingredient":"SESAME SEED","qty":0.1,"unit":"g","source_bulk_size":"1000","source_unit_price":"R66.95"},{"ingredient":"NORI","qty":2.0,"unit":"g","source_bulk_size":"100","source_unit_price":"R3.10"}],"page":2},{"name":"PINK BUTTERFLY 2025 8PC","sellingPrice":0.0,"ingredients":[{"ingredient":"CALIFORNIA ROLL","qty":8.0,"unit":"EACH","source_bulk_size":"8","source_unit_price":"R15.54"},{"ingredient":"PICKLED WATERMELON","qty":30.0,"unit":"g","source_bulk_size":"1000","source_unit_price":"79.99"},{"ingredient":"AVO","qty":0.25,"unit":"EACH","source_bulk_size":"1","source_unit_price":"R21.25"},{"ingredient":"SESAME SEED","qty":0.1,"unit":"g","source_bulk_size":"1000","source_unit_price":"R66.95"},{"ingredient":"PONZU MAYO","qty":10.0,"unit":"ml","source_bulk_size":"1000","source_unit_price":"R94.98"},{"ingredient":"TERIYAKI","qty":10.0,"unit":"g","source_bulk_size":"1000","source_unit_price":"R156.05"}],"page":2},{"name":"BRENTON SEA PLATTER 60PC","sellingPrice":1350.0,"ingredients":[{"ingredient":"SALMON CALIFORNIA","qty":12.0,"unit":"EACH","source_bulk_size":"4","source_unit_price":"R18.78"},{"ingredient":"PRAWN ROLL","qty":12.0,"unit":"EACH","source_bulk_size":"4","source_unit_price":"R11.99"},{"ingredient":"FUTOMAKI","qty":9.0,"unit":"EACH","source_bulk_size":"6","source_unit_price":"R11.99"},{"ingredient":"PRAWN TEMPURA","qty":15.0,"unit":"EACH","source_bulk_size":"4","source_unit_price":"R30.73"},{"ingredient":"TUNA NIGIRI","qty":6.0,"unit":"EACH","source_bulk_size":"2","source_unit_price":"R11.68"},{"ingredient":"ROCK SHRIMP","qty":6.0,"unit":"EACH","source_bulk_size":"4","source_unit_price":"R6.03"}],"page":2},{"name":"NIGIRI PLATTER 16PC","sellingPrice":220.0,"ingredients":[{"ingredient":"SALMON NIGIRI","qty":2.0,"unit":"EACH","source_bulk_size":"2","source_unit_price":"R16.18"},{"ingredient":"TUNA NIGIRI","qty":2.0,"unit":"EACH","source_bulk_size":"2","source_unit_price":"R11.68"},{"ingredient":"PRAWN NIGIRI","qty":2.0,"unit":"EACH","source_bulk_size":"2","source_unit_price":"R18.74"},{"ingredient":"AVO NIGIRI","qty":2.0,"unit":"EACH","source_bulk_size":"2","source_unit_price":"R8.27"},{"ingredient":"HAMACHI NIGIRI","qty":2.0,"unit":"EACH","source_bulk_size":"2","source_unit_price":"R6.74"},{"ingredient":"SQUID NIGIRI","qty":2.0,"unit":"EACH","source_bulk_size":"2","source_unit_price":""},{"ingredient":"OCTOPUS NIGIRI","qty":2.0,"unit":"EACH","source_bulk_size":"2","source_unit_price":""},{"ingredient":"EEL NIGIRI","qty":2.0,"unit":"EACH","source_bulk_size":"2","source_unit_price":""}],"page":2},{"name":"SASHIMI PLATTER 16PC","sellingPrice":285.0,"ingredients":[{"ingredient":"SALMON SASHIMI","qty":2.0,"unit":"EACH","source_bulk_size":"3","source_unit_price":"R25.34"},{"ingredient":"TUNA SASHIMI","qty":2.0,"unit":"EACH","source_bulk_size":"3","source_unit_price":"R18.90"},{"ingredient":"PRAWN","qty":2.0,"unit":"EACH","source_bulk_size":"2","source_unit_price":"R23.36"},{"ingredient":"HAMACHI","qty":2.0,"unit":"EACH","source_bulk_size":"3","source_unit_price":"R125.81"},{"ingredient":"OCTOPUS","qty":4.0,"unit":"EACH","source_bulk_size":"6","source_unit_price":"R14.00"}],"page":2},{"name":"TEMPURA PLATTER 6PC","sellingPrice":120.0,"ingredients":[{"ingredient":"TEMPURA SWEET POTATO","qty":30.0,"unit":"g","source_bulk_size":"1000","source_unit_price":"R29.65"},{"ingredient":"TEMPURA BRINGEL","qty":30.0,"unit":"g","source_bulk_size":"1000","source_unit_price":"R24.00"},{"ingredient":"TEMPURA MUSHROOM","qty":30.0,"unit":"g","source_bulk_size":"150","source_unit_price":"R34.99"},{"ingredient":"TEMPURA PRAWN","qty":1.0,"unit":"EACH","source_bulk_size":"1","source_unit_price":"R7.40"},{"ingredient":"TEMPURA TOFU","qty":30.0,"unit":"g","source_bulk_size":"1000","source_unit_price":"R49.00"},{"ingredient":"TEMPURA SAUCE","qty":20.0,"unit":"ml","source_bulk_size":"1000","source_unit_price":""}],"page":2},{"name":"MAKI PLATTER","sellingPrice":160.0,"ingredients":[{"ingredient":"SALMON MAKI & TOPPING","qty":2.0,"unit":"EACH","source_bulk_size":"4","source_unit_price":""},{"ingredient":"TUNA MAKI & TOPPING","qty":2.0,"unit":"EACH","source_bulk_size":"4","source_unit_price":""},{"ingredient":"PRAWN MAKI & TOPPING","qty":2.0,"unit":"EACH","source_bulk_size":"4","source_unit_price":""},{"ingredient":"AVO MAKI & TOPPING","qty":2.0,"unit":"EACH","source_bulk_size":"4","source_unit_price":""}],"page":2},{"name":"FRESH PLATTER","sellingPrice":0.0,"ingredients":[{"ingredient":"SALMON NIGIRI","qty":2.0,"unit":"EACH","source_bulk_size":"2","source_unit_price":"R16.18"},{"ingredient":"TUNA NIGIRI","qty":2.0,"unit":"EACH","source_bulk_size":"2","source_unit_price":"R11.68"},{"ingredient":"PRAWN NIGIRI","qty":2.0,"unit":"EACH","source_bulk_size":"2","source_unit_price":"R18.74"},{"ingredient":"HAMACHI NIGIRI","qty":2.0,"unit":"EACH","source_bulk_size":"2","source_unit_price":"R6.74"},{"ingredient":"SASHIMI SALMON","qty":2.0,"unit":"EACH","source_bulk_size":"3","source_unit_price":"R90.28"},{"ingredient":"SASHIMI TUNA","qty":2.0,"unit":"EACH","source_bulk_size":"3","source_unit_price":"R19.60"},{"ingredient":"SASHIMI HAMACHI","qty":2.0,"unit":"EACH","source_bulk_size":"3","source_unit_price":"R9.71"}],"page":2},{"name":"HAMACHI SASHIMI 3PC","sellingPrice":90.0,"ingredients":[{"ingredient":"HAMACHI","qty":60.0,"unit":"g","source_bulk_size":"1000","source_unit_price":"R125.81"},{"ingredient":"LETTUCE","qty":5.0,"unit":"g","source_bulk_size":"1000","source_unit_price":"R26.99"},{"ingredient":"SUSHI GARNISH","qty":5.0,"unit":"g","source_bulk_size":"1000","source_unit_price":"R6.13"}],"page":3},{"name":"HAMACHI NIGIRI2PC","sellingPrice":90.0,"ingredients":[{"ingredient":"HAMACHI","qty":30.0,"unit":"g","source_bulk_size":"1000","source_unit_price":"R125.81"},{"ingredient":"RICE","qty":40.0,"unit":"g","source_bulk_size":"1000","source_unit_price":"R24.03"}],"page":3},{"name":"HAMACHI SEARED SASHIMI 3PC","sellingPrice":90.0,"ingredients":[{"ingredient":"HAMACHI","qty":60.0,"unit":"g","source_bulk_size":"1000","source_unit_price":"R125.81"},{"ingredient":"LETTUCE","qty":5.0,"unit":"g","source_bulk_size":"1000","source_unit_price":"R26.99"},{"ingredient":"SUSHI GARNISH","qty":5.0,"unit":"g","source_bulk_size":"1000","source_unit_price":"R6.13"},{"ingredient":"SPRING ONION","qty":0.02,"unit":"EACH","source_bulk_size":"1","source_unit_price":"R16.45"},{"ingredient":"CAVIAR","qty":3.0,"unit":"g","source_bulk_size":"100","source_unit_price":"R202.75"},{"ingredient":"CITRUS DRESSING","qty":5.0,"unit":"g","source_bulk_size":"1000","source_unit_price":"R147.70"}],"page":3},{"name":"HAMACHI SEARED NIGRI 2PC","sellingPrice":90.0,"ingredients":[{"ingredient":"HAMACHI","qty":30.0,"unit":"g","source_bulk_size":"1000","source_unit_price":"R6.74"},{"ingredient":"RICE","qty":40.0,"unit":"g","source_bulk_size":"1000","source_unit_price":"R24.03"},{"ingredient":"SUSHI GARNISH","qty":5.0,"unit":"g","source_bulk_size":"1000","source_unit_price":"R6.13"},{"ingredient":"SPRING ONION","qty":0.02,"unit":"EACH","source_bulk_size":"1","source_unit_price":"R16.45"},{"ingredient":"CAVIAR","qty":3.0,"unit":"g","source_bulk_size":"100","source_unit_price":"R202.75"},{"ingredient":"CITRUS DRESSING","qty":5.0,"unit":"g","source_bulk_size":"1000","source_unit_price":"R147.70"}],"page":3},{"name":"HAMACHI MAKI 4PC","sellingPrice":90.0,"ingredients":[{"ingredient":"HAMACHI","qty":20.0,"unit":"g","source_bulk_size":"1000","source_unit_price":"R125.81"},{"ingredient":"RICE","qty":30.0,"unit":"g","source_bulk_size":"1000","source_unit_price":"R24.03"},{"ingredient":"SUSHI GARNISH","qty":5.0,"unit":"g","source_bulk_size":"1000","source_unit_price":"R6.13"},{"ingredient":"SPRING ONION","qty":0.02,"unit":"EACH","source_bulk_size":"1","source_unit_price":"R16.45"},{"ingredient":"CAVIAR","qty":3.0,"unit":"g","source_bulk_size":"100","source_unit_price":"R202.75"},{"ingredient":"CITRUS DRESSING","qty":5.0,"unit":"g","source_bulk_size":"1000","source_unit_price":"R147.70"}],"page":3},{"name":"OCTOPUS SASHIMI 6PC","sellingPrice":0.0,"ingredients":[{"ingredient":"OCTOPUS","qty":60.0,"unit":"g","source_bulk_size":"1000","source_unit_price":"R200.00"}],"page":3},{"name":"SALMON POKE BOWL","sellingPrice":185.0,"ingredients":[{"ingredient":"RICE","qty":250.0,"unit":"g","source_bulk_size":"1000","source_unit_price":"R24.03"},{"ingredient":"CUCUMBER","qty":30.0,"unit":"g","source_bulk_size":"503","source_unit_price":"R17.85"},{"ingredient":"CARROTS","qty":15.0,"unit":"g","source_bulk_size":"1000","source_unit_price":"R17.25"},{"ingredient":"RED CABBAGE","qty":20.0,"unit":"g","source_bulk_size":"814","source_unit_price":"R32.85"},{"ingredient":"EDAMAME","qty":30.0,"unit":"g","source_bulk_size":"1000","source_unit_price":"R69.60"},{"ingredient":"SWEET & SOUR PINE APPLE","qty":30.0,"unit":"g","source_bulk_size":"1000.00","source_unit_price":"R44.77"},{"ingredient":"SALMON","qty":50.0,"unit":"g","source_bulk_size":"700","source_unit_price":"R10.65"},{"ingredient":"AVO","qty":0.25,"unit":"EACH","source_bulk_size":"1","source_unit_price":"R21.25"},{"ingredient":"MUNG BEANS","qty":20.0,"unit":"g","source_bulk_size":"1000.00","source_unit_price":"R260.00"},{"ingredient":"GARNISH","qty":10.0,"unit":"g","source_bulk_size":"1000.00","source_unit_price":"R6.13"},{"ingredient":"TOGARASHI DRESSING","qty":40.0,"unit":"g","source_bulk_size":"1000.00","source_unit_price":"R432.00"},{"ingredient":"SESAME SEEDS","qty":6.0,"unit":"g","source_bulk_size":"1000.00","source_unit_price":"R66.95"}],"page":3},{"name":"TUNA POKE BOWL","sellingPrice":175.0,"ingredients":[{"ingredient":"RICE","qty":250.0,"unit":"g","source_bulk_size":"1000","source_unit_price":"R24.03"},{"ingredient":"CUCUMBER","qty":30.0,"unit":"g","source_bulk_size":"503","source_unit_price":"R17.85"},{"ingredient":"CARROTS","qty":15.0,"unit":"g","source_bulk_size":"1000","source_unit_price":"R17.25"},{"ingredient":"RED CABBAGE","qty":20.0,"unit":"g","source_bulk_size":"814","source_unit_price":"R32.85"},{"ingredient":"EDAMAME","qty":30.0,"unit":"g","source_bulk_size":"1000","source_unit_price":"R69.60"},{"ingredient":"SWEET & SOUR PINE APPLE","qty":30.0,"unit":"g","source_bulk_size":"1000.00","source_unit_price":"R44.77"},{"ingredient":"TUNA","qty":50.0,"unit":"g","source_bulk_size":"900","source_unit_price":"R261.55"},{"ingredient":"AVO","qty":0.25,"unit":"EACH","source_bulk_size":"1","source_unit_price":"R21.25"},{"ingredient":"MUNG BEANS","qty":10.0,"unit":"g","source_bulk_size":"1000.00","source_unit_price":"R260.00"},{"ingredient":"GARNISH","qty":10.0,"unit":"g","source_bulk_size":"1000.00","source_unit_price":"R6.13"},{"ingredient":"TOGARASHI DRESSING","qty":40.0,"unit":"g","source_bulk_size":"1000.00","source_unit_price":"R432.00"},{"ingredient":"SESAME SEEDS","qty":6.0,"unit":"g","source_bulk_size":"1000.00","source_unit_price":"R66.95"}],"page":3},{"name":"PRAWN POKE BOWL","sellingPrice":185.0,"ingredients":[{"ingredient":"RICE","qty":250.0,"unit":"g","source_bulk_size":"1000","source_unit_price":"R24.03"},{"ingredient":"CUCUMBER","qty":30.0,"unit":"g","source_bulk_size":"503","source_unit_price":"R17.85"},{"ingredient":"CARROTS","qty":15.0,"unit":"g","source_bulk_size":"1000","source_unit_price":"R17.25"},{"ingredient":"RED CABBAGE","qty":20.0,"unit":"g","source_bulk_size":"814","source_unit_price":"R32.85"},{"ingredient":"EDAMAME","qty":30.0,"unit":"g","source_bulk_size":"1000","source_unit_price":"R69.60"},{"ingredient":"SWEET & SOUR PINE APPLE","qty":30.0,"unit":"g","source_bulk_size":"1000.00","source_unit_price":"R44.77"},{"ingredient":"TEMPURA PRAWN","qty":2.0,"unit":"EACH","source_bulk_size":"1","source_unit_price":"R7.40"},{"ingredient":"AVO","qty":0.25,"unit":"EACH","source_bulk_size":"1","source_unit_price":"R21.25"},{"ingredient":"MUNG BEANS","qty":10.0,"unit":"g","source_bulk_size":"1000.00","source_unit_price":"R260.00"},{"ingredient":"GARNISH","qty":10.0,"unit":"g","source_bulk_size":"1000.00","source_unit_price":"R6.13"},{"ingredient":"TOGARASHI DRESSING","qty":40.0,"unit":"g","source_bulk_size":"1000.00","source_unit_price":"R432.00"},{"ingredient":"SESAME SEEDS","qty":6.0,"unit":"g","source_bulk_size":"1000.00","source_unit_price":"R66.95"}],"page":3},{"name":"MUSHROOM POKE BOWL","sellingPrice":160.0,"ingredients":[{"ingredient":"RICE","qty":250.0,"unit":"g","source_bulk_size":"1000","source_unit_price":"R24.03"},{"ingredient":"CUCUMBER","qty":30.0,"unit":"g","source_bulk_size":"503","source_unit_price":"R17.85"},{"ingredient":"CARROTS","qty":15.0,"unit":"g","source_bulk_size":"1000","source_unit_price":"R17.25"},{"ingredient":"RED CABBAGE","qty":20.0,"unit":"g","source_bulk_size":"814","source_unit_price":"R32.85"},{"ingredient":"EDAMAME","qty":30.0,"unit":"g","source_bulk_size":"1000","source_unit_price":"R69.60"},{"ingredient":"SWEET & SOUR PINE APPLE","qty":30.0,"unit":"g","source_bulk_size":"1000.00","source_unit_price":"R44.77"},{"ingredient":"PICKLED JAPANESE MUSHROOM","qty":50.0,"unit":"g","source_bulk_size":"1000","source_unit_price":"R305.21"},{"ingredient":"AVO","qty":0.25,"unit":"EACH","source_bulk_size":"1","source_unit_price":"R21.25"},{"ingredient":"MUNG BEANS","qty":10.0,"unit":"g","source_bulk_size":"1000.00","source_unit_price":"R260.00"},{"ingredient":"GARNISH","qty":10.0,"unit":"g","source_bulk_size":"1000.00","source_unit_price":"R6.13"},{"ingredient":"TOGARASHI DRESSING","qty":40.0,"unit":"g","source_bulk_size":"1000.00","source_unit_price":"R432.00"},{"ingredient":"SESAME SEEDS","qty":6.0,"unit":"g","source_bulk_size":"1000.00","source_unit_price":"R66.95"}],"page":3},{"name":"HAMACHI YELLOWTAIL PLATTER 12PC","sellingPrice":195.0,"ingredients":[{"ingredient":"HAMACHI SASHIMI","qty":2.0,"unit":"g","source_bulk_size":"1000","source_unit_price":"R9.71"},{"ingredient":"HAMACHI NIGIRI","qty":2.0,"unit":"g","source_bulk_size":"1000","source_unit_price":"R6.74"},{"ingredient":"HAMACHI SEARED SASHIMI","qty":2.0,"unit":"g","source_bulk_size":"1000","source_unit_price":"R16.86"},{"ingredient":"HAMACHI SEARED NIGIRI","qty":2.0,"unit":"g","source_bulk_size":"1000","source_unit_price":"R10.34"},{"ingredient":"HAMACHI MAKI","qty":4.0,"unit":"EACH","source_bulk_size":"4","source_unit_price":"R12.42"}],"page":3},{"name":"SAKE TASTING","sellingPrice":195.0,"ingredients":[{"ingredient":"SUNSET ROLL","qty":4.0,"unit":"EACH","source_bulk_size":"8","source_unit_price":"R58.04"},{"ingredient":"ROSES","qty":2.0,"unit":"EACH","source_bulk_size":"4","source_unit_price":"R22.89"},{"ingredient":"TUNA NIGIRI","qty":2.0,"unit":"EACH","source_bulk_size":"2","source_unit_price":"R11.68"},{"ingredient":"DRY ICE","qty":1.0,"unit":"g","source_bulk_size":"1000","source_unit_price":"R150.00"}],"page":3},{"name":"MACKEREL SAHIMI","sellingPrice":65.0,"ingredients":[{"ingredient":"MACKEREL","qty":60.0,"unit":"g","source_bulk_size":"700","source_unit_price":"R100.00"}],"page":4},{"name":"SCALLOP HAND ROLL","sellingPrice":65.0,"ingredients":[{"ingredient":"SCALLOP","qty":40.0,"unit":"g","source_bulk_size":"1000","source_unit_price":"R243.00"},{"ingredient":"SUSHI RICE","qty":30.0,"unit":"g","source_bulk_size":"1000","source_unit_price":"R24.03"},{"ingredient":"SRIRACHA MAYO","qty":5.0,"unit":"ml","source_bulk_size":"1000.00","source_unit_price":"R46.32"},{"ingredient":"NORI","qty":0.5,"unit":"EACH","source_bulk_size":"1","source_unit_price":"R3.10"}],"page":4},{"name":"SUNSET SCALLOP 4PC","sellingPrice":195.0,"ingredients":[{"ingredient":"CALIFORNIA ROLL 4PC","qty":4.0,"unit":"EACH","source_bulk_size":"8","source_unit_price":"R24.03"},{"ingredient":"PRAWN","qty":40.0,"unit":"g","source_bulk_size":"900","source_unit_price":"R284.04"},{"ingredient":"AVO","qty":0.25,"unit":"EACH","source_bulk_size":"1","source_unit_price":"R21.25"},{"ingredient":"SCALLOP","qty":20.0,"unit":"g","source_bulk_size":"750","source_unit_price":"R244.10"},{"ingredient":"SUNSET SAUCE","qty":30.0,"unit":"ml","source_bulk_size":"1000","source_unit_price":"R548.23"},{"ingredient":"PARSLEY","qty":0.002,"unit":"g","source_bulk_size":"1000.00","source_unit_price":"R180.00"},{"ingredient":"SESAME SEEDS","qty":2.0,"unit":"g","source_bulk_size":"1000","source_unit_price":"R66.95"}],"page":4},{"name":"4 SALMON GYOZA","sellingPrice":85.0,"ingredients":[{"ingredient":"SALMON MIX","qty":80.0,"unit":"g","source_bulk_size":"1000","source_unit_price":"R158.22"},{"ingredient":"CHILLI OIL","qty":20.0,"unit":"ml","source_bulk_size":"1000","source_unit_price":"R43.74"},{"ingredient":"GYOZA WRAPPER","qty":32.0,"unit":"g","source_bulk_size":"1000","source_unit_price":"R50.00"},{"ingredient":"DIPPING SAUCE","qty":60.0,"unit":"ml","source_bulk_size":"1000","source_unit_price":"R126.12"}],"page":4},{"name":"SUSHI PIZZA PRAWN","sellingPrice":85.0,"ingredients":[{"ingredient":"NORI","qty":1.0,"unit":"g","source_bulk_size":"100","source_unit_price":"R3.10"},{"ingredient":"RICE","qty":40.0,"unit":"g","source_bulk_size":"1000","source_unit_price":"R24.03"},{"ingredient":"TEMPURA BATTER","qty":40.0,"unit":"g","source_bulk_size":"1000","source_unit_price":"R1.98"},{"ingredient":"TEMPURA PRAWN","qty":1.0,"unit":"EACH","source_bulk_size":"1","source_unit_price":"R7.40"},{"ingredient":"AVO","qty":20.0,"unit":"g","source_bulk_size":"100","source_unit_price":"R21.25"},{"ingredient":"JAPANESE MAYO","qty":5.0,"unit":"ml","source_bulk_size":"500.00","source_unit_price":"R175.53"},{"ingredient":"TERIYAKI","qty":5.0,"unit":"g","source_bulk_size":"1000","source_unit_price":"R156.05"},{"ingredient":"SESAME SEEDS","qty":2.0,"unit":"g","source_bulk_size":"1000","source_unit_price":"R66.95"},{"ingredient":"AVO MAKI","qty":4.0,"unit":"EACH","source_bulk_size":"4","source_unit_price":"R6.38"}],"page":5},{"name":"SUSHI PIZZA SALMON","sellingPrice":95.0,"ingredients":[{"ingredient":"NORI","qty":1.0,"unit":"g","source_bulk_size":"100","source_unit_price":"R3.10"},{"ingredient":"RICE","qty":40.0,"unit":"g","source_bulk_size":"1000","source_unit_price":"R24.03"},{"ingredient":"TEMPURA BATTER","qty":40.0,"unit":"g","source_bulk_size":"1000","source_unit_price":"R19.81"},{"ingredient":"SALMON","qty":20.0,"unit":"g","source_bulk_size":"1000","source_unit_price":"R10.65"},{"ingredient":"AVO","qty":20.0,"unit":"g","source_bulk_size":"100","source_unit_price":"R21.25"},{"ingredient":"JAPANESE MAYO","qty":5.0,"unit":"ml","source_bulk_size":"500.00","source_unit_price":"R175.53"},{"ingredient":"TERIYAKI","qty":5.0,"unit":"g","source_bulk_size":"1000","source_unit_price":"R156.05"},{"ingredient":"SESAME SEEDS","qty":2.0,"unit":"g","source_bulk_size":"1000","source_unit_price":"R66.95"},{"ingredient":"AVO MAKI","qty":4.0,"unit":"EACH","source_bulk_size":"4","source_unit_price":"R6.38"}],"page":5},{"name":"SUSHI PIZZA VEG","sellingPrice":80.0,"ingredients":[{"ingredient":"NORI","qty":1.0,"unit":"g","source_bulk_size":"100","source_unit_price":"R3.10"},{"ingredient":"RICE","qty":40.0,"unit":"g","source_bulk_size":"1000","source_unit_price":"R24.03"},{"ingredient":"TEMPURA BATTER","qty":40.0,"unit":"g","source_bulk_size":"1000","source_unit_price":"R19.81"},{"ingredient":"RED PEPPER","qty":20.0,"unit":"g","source_bulk_size":"1000","source_unit_price":"R92.65"},{"ingredient":"AVO","qty":20.0,"unit":"g","source_bulk_size":"100","source_unit_price":"R21.25"},{"ingredient":"JAPANESE MAYO","qty":5.0,"unit":"ml","source_bulk_size":"500.00","source_unit_price":"R175.53"},{"ingredient":"ROCKET","qty":5.0,"unit":"g","source_bulk_size":"1000","source_unit_price":"R250.00"},{"ingredient":"SESAME SEEDS","qty":2.0,"unit":"g","source_bulk_size":"1000","source_unit_price":"R66.95"},{"ingredient":"AVO MAKI","qty":4.0,"unit":"EACH","source_bulk_size":"4","source_unit_price":"R6.38"}],"page":5},{"name":"SUSHI DESSERT 8PC","sellingPrice":80.0,"ingredients":[{"ingredient":"CALIFORNIA 8PC","qty":8.0,"unit":"EACH","source_bulk_size":"8","source_unit_price":""},{"ingredient":"COCONUT FLAKES","qty":5.0,"unit":"g","source_bulk_size":"1000","source_unit_price":"R77.99"},{"ingredient":"STRAWBERRIES","qty":35.0,"unit":"g","source_bulk_size":"1000","source_unit_price":"R33.35"},{"ingredient":"MANGO","qty":20.0,"unit":"g","source_bulk_size":"500","source_unit_price":"R29.00"},{"ingredient":"CREAM CHEESE","qty":10.0,"unit":"ml","source_bulk_size":"1000","source_unit_price":"R98.00"},{"ingredient":"PINEAPPLE SAUCE","qty":21.0,"unit":"ml","source_bulk_size":"1000.00","source_unit_price":""}],"page":5},{"name":"DON BURI SALMON","sellingPrice":180.0,"ingredients":[{"ingredient":"MARINATED SALMON COLLAR","qty":150.0,"unit":"g","source_bulk_size":"1000","source_unit_price":""},{"ingredient":"RICE","qty":130.0,"unit":"g","source_bulk_size":"1000","source_unit_price":"R24.03"},{"ingredient":"RED CABBAGE","qty":0.125,"unit":"EACH","source_bulk_size":"1","source_unit_price":"R32.85"},{"ingredient":"WHITE CABBAGE","qty":0.125,"unit":"EACH","source_bulk_size":"1","source_unit_price":"R22.65"},{"ingredient":"RED PEPPER","qty":15.0,"unit":"g","source_bulk_size":"1000","source_unit_price":"R92.65"},{"ingredient":"CARROTS","qty":20.0,"unit":"g","source_bulk_size":"1000","source_unit_price":"R17.25"},{"ingredient":"WHITE ONION","qty":20.0,"unit":"g","source_bulk_size":"1000","source_unit_price":"R12.86"},{"ingredient":"SESAME SEEDS","qty":5.0,"unit":"g","source_bulk_size":"1000","source_unit_price":"R66.95"},{"ingredient":"DRY ICE","qty":5.0,"unit":"g","source_bulk_size":"1000","source_unit_price":"R60.00"}],"page":6},{"name":"SUNOMONO SEAFOOD SALAD","sellingPrice":135.0,"ingredients":[{"ingredient":"SALMON","qty":15.0,"unit":"g","source_bulk_size":"700","source_unit_price":"R10.65"},{"ingredient":"TUNA","qty":15.0,"unit":"g","source_bulk_size":"900","source_unit_price":"R261.55"},{"ingredient":"PRAWN","qty":15.0,"unit":"g","source_bulk_size":"1000","source_unit_price":"R284.04"},{"ingredient":"CUCUMBER","qty":0.07,"unit":"EACH","source_bulk_size":"0.3","source_unit_price":"R17.85"},{"ingredient":"LETTUCE","qty":50.0,"unit":"g","source_bulk_size":"1000","source_unit_price":"R26.99"},{"ingredient":"GARLIC","qty":1.0,"unit":"g","source_bulk_size":"1000","source_unit_price":"R142.85"},{"ingredient":"GINGER","qty":1.0,"unit":"g","source_bulk_size":"1000","source_unit_price":"R149.99"},{"ingredient":"SOYA","qty":10.0,"unit":"g","source_bulk_size":"1000","source_unit_price":"R135.00"},{"ingredient":"RICE WINE VINEGAR","qty":10.0,"unit":"ml","source_bulk_size":"1000","source_unit_price":"R49.80"},{"ingredient":"SALT","qty":0.5,"unit":"g","source_bulk_size":"1000","source_unit_price":"R15.99"},{"ingredient":"WAKAME","qty":5.0,"unit":"g","source_bulk_size":"1000","source_unit_price":"R725.00"},{"ingredient":"AVO","qty":0.125,"unit":"EACH","source_bulk_size":"1","source_unit_price":"R21.25"}],"page":6},{"name":"SALMON TACO","sellingPrice":85.0,"ingredients":[{"ingredient":"NORI","qty":1.0,"unit":"g","source_bulk_size":"100","source_unit_price":"R3.10"},{"ingredient":"RICE","qty":30.0,"unit":"g","source_bulk_size":"1000","source_unit_price":"R24.03"},{"ingredient":"SALMON","qty":30.0,"unit":"g","source_bulk_size":"700","source_unit_price":"R10.65"},{"ingredient":"AVO","qty":0.062,"unit":"EACH","source_bulk_size":"1","source_unit_price":"R21.25"},{"ingredient":"JAPANESE MAYO","qty":5.0,"unit":"ml","source_bulk_size":"450","source_unit_price":"R175.53"},{"ingredient":"CREAM CHEESE","qty":5.0,"unit":"ml","source_bulk_size":"1000","source_unit_price":"R98.00"},{"ingredient":"JALAPENO","qty":2.0,"unit":"g","source_bulk_size":"1000","source_unit_price":"R21.19"},{"ingredient":"TEMPURA BATTTER","qty":10.0,"unit":"g","source_bulk_size":"1000","source_unit_price":"R1.98"}],"page":6},{"name":"CHIKEJN GYOZA","sellingPrice":85.0,"ingredients":[{"ingredient":"GYOZA WRAPPER","qty":3.0,"unit":"g","source_bulk_size":"300","source_unit_price":"R50.00"},{"ingredient":"MARINATED CHICKEN","qty":20.0,"unit":"g","source_bulk_size":"500","source_unit_price":"R0.10"}],"page":7}],"count":90,"engine":"Structured PDF reader"}
